[
  {
    "title": "LIFE at SERE2026: European Conference on Ecological Restoration",
    "date": "2026-08-24",
    "end_date": "2026-08-28",
    "date_label": "24-28 Aug 2026",
    "type": "Conferences and summits",
    "venue": "European Conference on Ecological Restoration Brest, France",
    "link": "https://cinea.ec.europa.eu/news-events/events/life-sere2026-european-conference-ecological-restoration-2026-08-24_en",
    "source": "CINEA homepage events"
  },
  {
    "title": "LIFE RIPARIAS final conference",
    "date": "2026-09-08",
    "end_date": "2026-09-09",
    "date_label": "08-09 Sep 2026",
    "type": "Conferences and summits",
    "venue": "Conferences and summits LIFE RIPARIAS final conference Brussels, Belgium",
    "link": "https://cinea.ec.europa.eu/news-events/events/life-riparias-final-conference-2026-09-08_en",
    "source": "CINEA homepage events"
  },
  {
    "title": "Rivers of LIFE final seminar",
    "date": "2026-09-15",
    "end_date": "2026-09-17",
    "date_label": "15-17 Sep 2026",
    "type": "Expert meetings",
    "venue": "Brussels, Belgium See all our events Publications",
    "link": "https://cinea.ec.europa.eu/news-events/events/rivers-life-final-seminar-2026-09-15_en",
    "source": "CINEA homepage events"
  }
]